traceloggerx/__init__.py
traceloggerx/logutils/__init__.py
traceloggerx/logutils/formatter.py
traceloggerx/logutils/handlers.py
traceloggerx/logutils/logger.py
traceloggerx-0.1.8.dist-info/licenses/LICENSE
traceloggerx-0.1.8.dist-info/METADATA
traceloggerx-0.1.8.dist-info/WHEEL
traceloggerx-0.1.8.dist-info/top_level.txt
traceloggerx-0.1.8.dist-info/RECORD
