Metadata-Version: 2.4
Name: traceloggerx
Version: 0.1.8
Summary: Structured JSON logger with trace_id, user_id and colored console output.
Author-email: Daye <daye@example.com>
License: MIT
Requires-Python: >=3.8
License-File: LICENSE
Requires-Dist: colorlog
Dynamic: license-file
